app/__init__ - Copy.py
app/__init__.py
app/fetcher - Copy.py
app/fetcher.py
app/fudstop_info - Copy.py
app/fudstop_info.py
app/helpers - Copy.py
app/helpers.py
fudstop/__init__.py
fudstop/all_helpers.py
fudstop/options_filter.py
fudstop/plots.py
fudstop/schema.py
fudstop/_gpts/__init__ - Copy.py
fudstop/_gpts/__init__.py
fudstop/_gpts/trader_ai - Copy.py
fudstop/_gpts/trader_ai.py
fudstop/_markets/__init__ - Copy.py
fudstop/_markets/__init__.py
fudstop/_markets/analyzers - Copy.py
fudstop/_markets/analyzers.py
fudstop/_markets/embeddings - Copy.py
fudstop/_markets/embeddings.py
fudstop/_markets/monitor - Copy.py
fudstop/_markets/monitor.py
fudstop/_markets/multimarkets - Copy.py
fudstop/_markets/multimarkets.py
fudstop/_markets/stock_market - Copy.py
fudstop/_markets/stock_market.py
fudstop/_markets/webhook_dicts - Copy.py
fudstop/_markets/webhook_dicts.py
fudstop/_markets/finished/__init__.py
fudstop/_markets/finished/db_manager.py
fudstop/_markets/finished/economic_data.py
fudstop/_markets/finished/master_class.py
fudstop/_markets/finished/td9_states.py
fudstop/_markets/list_sets/__init__.py
fudstop/_markets/list_sets/dicts.py
fudstop/_markets/list_sets/saved_tickers.py
fudstop/_markets/list_sets/ticker_lists.py
fudstop/_markets/market_handlers/__init__ - Copy.py
fudstop/_markets/market_handlers/__init__.py
fudstop/_markets/market_handlers/cfg.py
fudstop/_markets/market_handlers/crypto.py
fudstop/_markets/market_handlers/database_.py
fudstop/_markets/market_handlers/forex.py
fudstop/_markets/market_handlers/indices.py
fudstop/_markets/market_handlers/list_sets.py
fudstop/_markets/market_handlers/options.py
fudstop/_markets/market_handlers/stocks.py
fudstop/_markets/plotting/__init__ - Copy.py
fudstop/_markets/plotting/__init__.py
fudstop/_markets/reference_markets/__init__ - Copy.py
fudstop/_markets/reference_markets/__init__.py
fudstop/_markets/reference_markets/conditional_scans - Copy.py
fudstop/_markets/reference_markets/conditional_scans.py
fudstop-5.9.9.dist-info/METADATA
fudstop-5.9.9.dist-info/WHEEL
fudstop-5.9.9.dist-info/top_level.txt
fudstop-5.9.9.dist-info/RECORD
